{
  "pokemon": [
    {
      "name": "Bulbasaur",
      "type": "Grass",
      "type2": "Poison",
      "attack": "Razor Leaf",
      "level": 14,
      "id": "bulbasaur"
    },
    {
      "name": "Squirtle",
      "type": "Water",
      "attack": "Water gun",
      "level": 28,
      "id": "squirtle"
    },
    {
      "name": "Charmander",
      "type": "Fire",
      "attack": "Ember",
      "level": 16,
      "id": "charmander"
    },
    {
      "name": "mudkip",
      "type": "water",
      "type2": "",
      "attack": "water gun",
      "level": 500,
      "id": "mudkip"
    },
    {
      "name": "marshtomp",
      "type": "water",
      "type2": "ground",
      "attack": "mud slap",
      "level": 5,
      "id": "marshtomp"
    },
    {
      "name": "swampert",
      "type": "water",
      "type2": "ground",
      "attack": "earthquake",
      "level": 5,
      "id": "swampert"
    },
    {
      "name": "charizard",
      "type": "fire",
      "type2": "flying",
      "attack": "flamethrower",
      "level": 5,
      "id": "charizard"
    },
    {
      "name": "deoxys-attack",
      "type": "psychic",
      "type2": "",
      "attack": "confusion",
      "level": 5,
      "id": "deoxys-attack"
    }
  ]
}